keepsake_ui/__init__.py
keepsake_ui/app.py
keepsake_ui/main.py
keepsake_ui/templates/base.html
keepsake_ui/templates/compare.html
keepsake_ui/templates/error.html
keepsake_ui/templates/experiment.html
keepsake_ui/templates/experiment_list.html
keepsake_ui-0.0.1.dist-info/LICENCE
keepsake_ui-0.0.1.dist-info/METADATA
keepsake_ui-0.0.1.dist-info/WHEEL
keepsake_ui-0.0.1.dist-info/entry_points.txt
keepsake_ui-0.0.1.dist-info/top_level.txt
keepsake_ui-0.0.1.dist-info/RECORD
