Metadata-Version: 2.1
Name: keepsake-ui
Version: 0.0.1
Summary: Web UI to keepsake tool.
Home-page: https://github.com/jsemric/keepsake-ui
Author: Jakub Semric
Author-email: jakubsemric@gmail.com
License: Apache License 2.0
Platform: UNKNOWN
Requires-Python: >=3.6.0
License-File: LICENCE
Requires-Dist: gunicorn (~=20.1.0)
Requires-Dist: keepsake (~=0.4.2)
Requires-Dist: flask (~=2.0.2)
